odoo/addons/partner_priority/README.rst
odoo/addons/partner_priority/__init__.py
odoo/addons/partner_priority/__manifest__.py
odoo/addons/partner_priority/data/partner_priority_data.xml
odoo/addons/partner_priority/data/partner_priority_sequence_data.xml
odoo/addons/partner_priority/i18n/ca.po
odoo/addons/partner_priority/i18n/es.po
odoo/addons/partner_priority/i18n/partner_priority.pot
odoo/addons/partner_priority/models/__init__.py
odoo/addons/partner_priority/models/partner_priority.py
odoo/addons/partner_priority/models/res_partner.py
odoo/addons/partner_priority/readme/CONTRIBUTORS.rst
odoo/addons/partner_priority/readme/DESCRIPTION.rst
odoo/addons/partner_priority/readme/USAGE.rst
odoo/addons/partner_priority/security/ir.model.access.csv
odoo/addons/partner_priority/static/description/icon.png
odoo/addons/partner_priority/static/description/index.html
odoo/addons/partner_priority/views/partner_priority.xml
odoo/addons/partner_priority/views/res_partner.xml
odoo13_addon_partner_priority-13.0.1.0.1.dev7.dist-info/METADATA
odoo13_addon_partner_priority-13.0.1.0.1.dev7.dist-info/WHEEL
odoo13_addon_partner_priority-13.0.1.0.1.dev7.dist-info/top_level.txt
odoo13_addon_partner_priority-13.0.1.0.1.dev7.dist-info/RECORD
